{"trial_id": "0", "hyperparameters": {"space": [{"class_name": "Int", "config": {"name": "nb_neurons1", "default": null, "conditions": [], "min_value": 20, "max_value": 128, "step": 20, "sampling": "linear"}}, {"class_name": "Int", "config": {"name": "nb_neurons2", "default": null, "conditions": [], "min_value": 20, "max_value": 128, "step": 20, "sampling": "linear"}}, {"class_name": "Int", "config": {"name": "dense_neurons", "default": null, "conditions": [], "min_value": 100, "max_value": 300, "step": 20, "sampling": "linear"}}, {"class_name": "Int", "config": {"name": "epochs", "default": 10, "conditions": [], "min_value": 5, "max_value": 20, "step": 1, "sampling": "linear"}}, {"class_name": "Choice", "config": {"name": "learning_rate", "default": 0.001, "conditions": [], "values": [0.001, 0.0001, 1e-05], "ordered": true}}, {"class_name": "Boolean", "config": {"name": "dopout", "default": false, "conditions": []}}], "values": {"nb_neurons1": 120, "nb_neurons2": 100, "dense_neurons": 220, "epochs": 14, "learning_rate": 0.0001, "dopout": true}}, "metrics": {"metrics": {}}, "score": null, "best_step": 0, "status": "RUNNING", "message": null}